MANIFEST.in
requirements.txt
setup.cfg
setup.py
flask_magic/__about__.py
flask_magic/__init__.py
flask_magic/cli.py
flask_magic/core.py
flask_magic/decorators.py
flask_magic/exceptions.py
flask_magic/ext.py
flask_magic/utils.py
flask_magic.egg-info/PKG-INFO
flask_magic.egg-info/SOURCES.txt
flask_magic.egg-info/dependency_links.txt
flask_magic.egg-info/entry_points.txt
flask_magic.egg-info/not-zip-safe
flask_magic.egg-info/requires.txt
flask_magic.egg-info/top_level.txt
flask_magic/app-skel/app.py
flask_magic/app-skel/blank
flask_magic/app-skel/config.py
flask_magic/app-skel/gitignore
flask_magic/app-skel/magic.py
flask_magic/app-skel/magic.yml
flask_magic/app-skel/model.py
flask_magic/app-skel/propel.yml
flask_magic/app-skel/_data/mail-templates/contact-us.txt
flask_magic/app-skel/_data/mail-templates/default-template.txt
flask_magic/app-skel/_data/mail-templates/reset-password.txt
flask_magic/app-skel/_data/mail-templates/welcome-admin.txt
flask_magic/app-skel/_data/mail-templates/welcome.txt
flask_magic/app-skel/_data/uploads/empty
flask_magic/app-skel/skel/api/__init__.py
flask_magic/app-skel/skel/api/views.py
flask_magic/app-skel/skel/app/__init__.py
flask_magic/app-skel/skel/app/views.py
flask_magic/app-skel/skel/app/static/assets.yml
flask_magic/app-skel/skel/app/static/css/admin.css
flask_magic/app-skel/skel/app/static/css/style.css
flask_magic/app-skel/skel/app/static/images/blank
flask_magic/app-skel/skel/app/static/js/admin.js
flask_magic/app-skel/skel/app/static/js/app.js
flask_magic/app-skel/skel/app/templates/layout.html
flask_magic/app-skel/skel/app/templates/macros.html
flask_magic/app-skel/skel/app/templates/Index/index.html
flask_magic/extras/__init__.py
flask_magic/extras/htmlcompress.py
flask_magic/extras/markdown_ext.py
flask_magic/plugins/__init__.py
flask_magic/plugins/base/__init__.py
flask_magic/plugins/base/static/assets.yml
flask_magic/plugins/base/static/Magic/.bowerrc
flask_magic/plugins/base/static/Magic/bower.json
flask_magic/plugins/base/static/Magic/authomatic/authomatic.js
flask_magic/plugins/base/static/Magic/bootstrap/.bower.json
flask_magic/plugins/base/static/Magic/bootstrap/CHANGELOG.md
flask_magic/plugins/base/static/Magic/bootstrap/Gruntfile.js
