Metadata-Version: 1.1
Name: flask-magic
Version: 0.0.53
Summary: A full stack Flask based framework that put structure in the file system. Features: Caching, Mailing, Storage, CSRF, recaptcha and more
Home-page: https://github.com/mardix/flask-magic
Author: Mardix
Author-email: mardix@pylot.io
License: MIT
Keywords: flask,juice,templates,views,classy,framework,mvc,blueprint,magic
Platform: any
Classifier: Environment :: Web Environment
Classifier: Intended Audience :: Developers
Classifier: License :: OSI Approved :: BSD License
Classifier: Operating System :: OS Independent
Classifier: Programming Language :: Python
Classifier: Programming Language :: Python :: 2
Classifier: Programming Language :: Python :: 2.6
Classifier: Programming Language :: Python :: 2.7
Classifier: Programming Language :: Python :: 3
Classifier: Programming Language :: Python :: 3.3
Classifier: Programming Language :: Python :: 3.4
Classifier: Topic :: Internet :: WWW/HTTP :: Dynamic Content
Classifier: Topic :: Software Development :: Libraries :: Python Modules
